pwp_packs/__init__.py
pwp_packs/screenrecorder.py
pwp_packs/version.py
pwp_packs-0.0.4.dist-info/LICENSE
pwp_packs-0.0.4.dist-info/METADATA
pwp_packs-0.0.4.dist-info/WHEEL
pwp_packs-0.0.4.dist-info/top_level.txt
pwp_packs-0.0.4.dist-info/RECORD
