Metadata-Version: 2.1
Name: pwp_packs
Version: 0.0.4
Summary: utility tool - Screen Recorder
Author-email: "ProgresswithPython (Vivek Kumar)" <kumarvivek9088@gmail.com>
Keywords: python,screen recorder,video,audio,ffmpeg,screen_recorder,pwp_packs,screenrecorder,screenrecordergui
Classifier: Programming Language :: Python :: 3
Classifier: License :: OSI Approved :: MIT License
Classifier: Operating System :: OS Independent
Requires-Python: >=3.5
License-File: LICENSE
Requires-Dist: imageio-ffmpeg
Requires-Dist: pyautogui
